readmemd2txt/aboutproject.py
readmemd2txt/readmemd2txt.py
readmemd2txt-0.0.5.dist-info/entry_points.txt
readmemd2txt-0.0.5.dist-info/LICENSE
readmemd2txt-0.0.5.dist-info/WHEEL
readmemd2txt-0.0.5.dist-info/METADATA
readmemd2txt-0.0.5.dist-info/RECORD
